CHANGELOG.txt
LICENCE.txt
MANIFEST.in
README.md
requirements.txt
setup.py
ipyxt/__init__.py
ipyxt/ding.mp3
ipyxt/error.mp3
ipyxt.egg-info/PKG-INFO
ipyxt.egg-info/SOURCES.txt
ipyxt.egg-info/dependency_links.txt
ipyxt.egg-info/top_level.txt
venv/bin/activate_this.py
venv/bin/rst2html.py
venv/bin/rst2html4.py
venv/bin/rst2html5.py
venv/bin/rst2latex.py
venv/bin/rst2man.py
venv/bin/rst2odt.py
venv/bin/rst2odt_prepstyles.py
venv/bin/rst2pseudoxml.py
venv/bin/rst2s5.py
venv/bin/rst2xetex.py
venv/bin/rst2xml.py
venv/bin/rstpep2html.py
venv/lib/python3.8/site-packages/_virtualenv.py
venv/lib/python3.8/site-packages/decorator.py
venv/lib/python3.8/site-packages/pickleshare.py
venv/lib/python3.8/site-packages/six.py
venv/lib/python3.8/site-packages/zipp.py
venv/lib/python3.8/site-packages/IPython/__init__.py
venv/lib/python3.8/site-packages/IPython/__main__.py
venv/lib/python3.8/site-packages/IPython/config.py
venv/lib/python3.8/site-packages/IPython/conftest.py
venv/lib/python3.8/site-packages/IPython/consoleapp.py
venv/lib/python3.8/site-packages/IPython/display.py
venv/lib/python3.8/site-packages/IPython/frontend.py
venv/lib/python3.8/site-packages/IPython/html.py
venv/lib/python3.8/site-packages/IPython/nbconvert.py
venv/lib/python3.8/site-packages/IPython/nbformat.py
venv/lib/python3.8/site-packages/IPython/parallel.py
venv/lib/python3.8/site-packages/IPython/paths.py
venv/lib/python3.8/site-packages/IPython/qt.py
venv/lib/python3.8/site-packages/IPython/core/__init__.py
venv/lib/python3.8/site-packages/IPython/core/alias.py
venv/lib/python3.8/site-packages/IPython/core/application.py
venv/lib/python3.8/site-packages/IPython/core/async_helpers.py
venv/lib/python3.8/site-packages/IPython/core/autocall.py
venv/lib/python3.8/site-packages/IPython/core/builtin_trap.py
venv/lib/python3.8/site-packages/IPython/core/compilerop.py
venv/lib/python3.8/site-packages/IPython/core/completer.py
venv/lib/python3.8/site-packages/IPython/core/completerlib.py
venv/lib/python3.8/site-packages/IPython/core/crashhandler.py
venv/lib/python3.8/site-packages/IPython/core/debugger.py
venv/lib/python3.8/site-packages/Pygments-2.10.0.dist-info/entry_points.txt
venv/lib/python3.8/site-packages/Pygments-2.10.0.dist-info/top_level.txt
venv/lib/python3.8/site-packages/appnope-0.1.2.dist-info/top_level.txt
venv/lib/python3.8/site-packages/bleach-4.1.0.dist-info/top_level.txt
venv/lib/python3.8/site-packages/bleach/_vendor/html5lib-1.1.dist-info/top_level.txt
venv/lib/python3.8/site-packages/certifi-2021.10.8.dist-info/top_level.txt
venv/lib/python3.8/site-packages/charset_normalizer-2.0.7.dist-info/entry_points.txt
venv/lib/python3.8/site-packages/charset_normalizer-2.0.7.dist-info/top_level.txt
venv/lib/python3.8/site-packages/colorama-0.4.4.dist-info/LICENSE.txt
venv/lib/python3.8/site-packages/colorama-0.4.4.dist-info/top_level.txt
venv/lib/python3.8/site-packages/decorator-5.1.0.dist-info/LICENSE.txt
venv/lib/python3.8/site-packages/decorator-5.1.0.dist-info/top_level.txt
venv/lib/python3.8/site-packages/docutils-0.17.1.dist-info/COPYING.txt
venv/lib/python3.8/site-packages/docutils-0.17.1.dist-info/top_level.txt
venv/lib/python3.8/site-packages/idna-3.3.dist-info/LICENSE.md
venv/lib/python3.8/site-packages/idna-3.3.dist-info/top_level.txt
venv/lib/python3.8/site-packages/importlib_metadata-4.8.1.dist-info/top_level.txt
venv/lib/python3.8/site-packages/ipython-7.28.0.dist-info/entry_points.txt
venv/lib/python3.8/site-packages/ipython-7.28.0.dist-info/top_level.txt
venv/lib/python3.8/site-packages/jedi-0.18.0.dist-info/AUTHORS.txt
venv/lib/python3.8/site-packages/jedi-0.18.0.dist-info/LICENSE.txt
venv/lib/python3.8/site-packages/jedi-0.18.0.dist-info/top_level.txt
venv/lib/python3.8/site-packages/keyring-23.2.1.dist-info/entry_points.txt
venv/lib/python3.8/site-packages/keyring-23.2.1.dist-info/top_level.txt
venv/lib/python3.8/site-packages/matplotlib_inline-0.1.3.dist-info/top_level.txt
venv/lib/python3.8/site-packages/packaging-21.0.dist-info/top_level.txt
venv/lib/python3.8/site-packages/parso-0.8.2.dist-info/AUTHORS.txt
venv/lib/python3.8/site-packages/parso-0.8.2.dist-info/LICENSE.txt
venv/lib/python3.8/site-packages/parso-0.8.2.dist-info/top_level.txt
venv/lib/python3.8/site-packages/pexpect-4.8.0.dist-info/top_level.txt
venv/lib/python3.8/site-packages/pickleshare-0.7.5.dist-info/top_level.txt
venv/lib/python3.8/site-packages/pip-21.3.1.dist-info/LICENSE.txt
venv/lib/python3.8/site-packages/pip-21.3.1.dist-info/entry_points.txt
venv/lib/python3.8/site-packages/pip-21.3.1.dist-info/top_level.txt
venv/lib/python3.8/site-packages/pkginfo-1.7.1.dist-info/LICENSE.txt
venv/lib/python3.8/site-packages/pkginfo-1.7.1.dist-info/entry_points.txt
venv/lib/python3.8/site-packages/pkginfo-1.7.1.dist-info/top_level.txt
venv/lib/python3.8/site-packages/prompt_toolkit-3.0.21.dist-info/top_level.txt
venv/lib/python3.8/site-packages/pyparsing-3.0.1.dist-info/top_level.txt
venv/lib/python3.8/site-packages/readme_renderer-30.0.dist-info/entry_points.txt
venv/lib/python3.8/site-packages/readme_renderer-30.0.dist-info/top_level.txt
venv/lib/python3.8/site-packages/requests-2.26.0.dist-info/top_level.txt
venv/lib/python3.8/site-packages/requests_toolbelt-0.9.1.dist-info/top_level.txt
venv/lib/python3.8/site-packages/rfc3986-1.5.0.dist-info/top_level.txt
venv/lib/python3.8/site-packages/setuptools-57.0.0.dist-info/dependency_links.txt
venv/lib/python3.8/site-packages/setuptools-57.0.0.dist-info/entry_points.txt
venv/lib/python3.8/site-packages/setuptools-57.0.0.dist-info/top_level.txt
venv/lib/python3.8/site-packages/six-1.16.0.dist-info/top_level.txt
venv/lib/python3.8/site-packages/tqdm-4.62.3.dist-info/entry_points.txt
venv/lib/python3.8/site-packages/tqdm-4.62.3.dist-info/top_level.txt
venv/lib/python3.8/site-packages/traitlets-5.1.1.dist-info/COPYING.md
venv/lib/python3.8/site-packages/traitlets-5.1.1.dist-info/top_level.txt
venv/lib/python3.8/site-packages/twine-3.4.2.dist-info/entry_points.txt
