Metadata-Version: 2.1
Name: ipyxt
Version: 0.0.7
Summary: IPython extensions
Home-page: UNKNOWN
Author: Esteban Uri
Author-email: estebanuri@gmail.com
License: MIT
Keywords: ipython extensions
Platform: UNKNOWN
Classifier: Development Status :: 5 - Production/Stable
Classifier: License :: OSI Approved :: MIT License
Classifier: Programming Language :: Python :: 3
